LICENSE
README.md
setup.py
yaw_sweep_sg_cali/Calibration_factors.py
yaw_sweep_sg_cali/Curve_fitting.py
yaw_sweep_sg_cali/Load_data.py
yaw_sweep_sg_cali/SQL_utilities.py
yaw_sweep_sg_cali/Yaw_sweep_identification.py
yaw_sweep_sg_cali/__init__.py
yaw_sweep_sg_cali.egg-info/PKG-INFO
yaw_sweep_sg_cali.egg-info/SOURCES.txt
yaw_sweep_sg_cali.egg-info/dependency_links.txt
yaw_sweep_sg_cali.egg-info/requires.txt
yaw_sweep_sg_cali.egg-info/top_level.txt