Metadata-Version: 2.1
Name: yaw-sweep-sg-cali
Version: 2.2
Summary: Package to generate the strain gauge calibration factors when those are placed on wind turbine towers. Based on idling operations, so called, yaw sweeps.
Author: Bruno and Zahra
Author-email: brofa@dtu.dk
License-File: LICENSE
